pyF3D/ClAttributes.py
pyF3D/FilterAttributes.py
pyF3D/FilterClasses.py
pyF3D/FilterManager.py
pyF3D/__init__.py
pyF3D/pipeline.py
pyF3D/OpenCL/BilateralFiltering.cl
pyF3D/OpenCL/FFTFilter.cl
pyF3D/OpenCL/MMdil3D.cl
pyF3D/OpenCL/MMero3D.cl
pyF3D/OpenCL/Mask3D.cl
pyF3D/OpenCL/MedianFilter.cl
pyF3D/OpenCL/__init__.py
pyF3D/filters/BilateralFilter.py
pyF3D/filters/FFTFilter.py
pyF3D/filters/MMFilterClo.py
pyF3D/filters/MMFilterDil.py
pyF3D/filters/MMFilterEro.py
pyF3D/filters/MMFilterOpe.py
pyF3D/filters/MaskFilter.py
pyF3D/filters/MedianFilter.py
pyF3D/filters/__init__.py
pyf3d-1.0.3.dist-info/DESCRIPTION.rst
pyf3d-1.0.3.dist-info/METADATA
pyf3d-1.0.3.dist-info/RECORD
pyf3d-1.0.3.dist-info/WHEEL
pyf3d-1.0.3.dist-info/metadata.json
pyf3d-1.0.3.dist-info/top_level.txt
