Metadata-Version: 2.0
Name: pyf3d
Version: 1.0.3
Summary: Filtering for micro-tomography data
Home-page: https://github.com/holdymoldy/pyF3D
Author: Holden Parks
Author-email: hparks@lbl.gov
License: BSD
Platform: UNKNOWN
Classifier: Development Status :: 3 - Alpha
Classifier: License :: OSI Approved :: BSD License
Classifier: Intended Audience :: Science/Research
Classifier: Programming Language :: Python :: 2
Classifier: Programming Language :: Python :: 2.7
Requires-Dist: futures
Requires-Dist: numpy
Requires-Dist: pyopencl
